MANIFEST.in
setup.py
dagcategory/__init__.py
dagcategory/admin.py
dagcategory/models.py
dagcategory/tests.py
dagcategory/views.py
dagcategory/templates/admin/category_hierarchy.html
dagcategory/templates/admin/dagcategory/dagcategory/change_list.html
dagcategory/templatetags/__init__.py
dagcategory/templatetags/category.py
django_dagcategory.egg-info/PKG-INFO
django_dagcategory.egg-info/SOURCES.txt
django_dagcategory.egg-info/dependency_links.txt
django_dagcategory.egg-info/top_level.txt
django_dagcategory.egg-info/zip-safe