Metadata-Version: 1.0
Name: django-dagcategory
Version: 0.0.2
Summary: A simple library for creating tree like categories
Home-page: http://github.com/cuker/django-dagcategory
Author: Jason Kraus
Author-email: zbyte64@gmail.com
License: New BSD License
Keywords: django category
Platform: UNKNOWN
Classifier: Programming Language :: Python
Classifier: Operating System :: OS Independent
Classifier: Natural Language :: English
Classifier: Development Status :: 3 - Alpha
Classifier: Intended Audience :: Developers
Classifier: Topic :: Internet :: WWW/HTTP :: Dynamic Content
